willamette_common/__init__.py
willamette_common/schemas/__init__.py
willamette_common/schemas/api_v1/__init__.py
willamette_common/schemas/api_v1/web_pages.py
willamette_common/schemas/api_v1/web_sites.py
willamette_common/schemas/api_v1/mixins/__init__.py
willamette_common/schemas/api_v1/mixins/common.py
willamette_common/schemas/api_v1/mixins/web_pages.py
willamette_common/schemas/api_v1/mixins/web_sites.py
quaerere_willamette_common-0.2.1.post1.dist-info/LICENSE.txt
quaerere_willamette_common-0.2.1.post1.dist-info/METADATA
quaerere_willamette_common-0.2.1.post1.dist-info/WHEEL
quaerere_willamette_common-0.2.1.post1.dist-info/entry_points.txt
quaerere_willamette_common-0.2.1.post1.dist-info/top_level.txt
quaerere_willamette_common-0.2.1.post1.dist-info/RECORD
